inferedge_moss/__init__.py
inferedge_moss/__init__.pyi
inferedge_moss/py.typed
inferedge_moss/client/moss_client.py
inferedge_moss/services/__init__.py
inferedge_moss/services/embedding_service.py
inferedge_moss/services/index_service.py
inferedge_moss/services/moss_service.py
inferedge_moss/utils/cloud_api_client.py
inferedge_moss/utils/serializers.py
moss_client/__init__.py
moss_client-1.0.0b9.dist-info/licenses/LICENSE.txt
moss_client-1.0.0b9.dist-info/METADATA
moss_client-1.0.0b9.dist-info/WHEEL
moss_client-1.0.0b9.dist-info/top_level.txt
moss_client-1.0.0b9.dist-info/RECORD
